MANIFEST.in
README.rst
setup.py
minibooks/__init__.py
minibooks/models.py
minibooks/urls.py
minibooks.egg-info/PKG-INFO
minibooks.egg-info/SOURCES.txt
minibooks.egg-info/dependency_links.txt
minibooks.egg-info/top_level.txt
minibooks/call_log/__init__.py
minibooks/call_log/models.py
minibooks/call_log/urls.py
minibooks/call_log/views.py
minibooks/ledger/__init__.py
minibooks/ledger/admin.py
minibooks/ledger/communication.py
minibooks/ledger/cron.py
minibooks/ledger/demo.py
minibooks/ledger/forms.py
minibooks/ledger/models.py
minibooks/ledger/pdf_latex.py
minibooks/ledger/report.py
minibooks/ledger/test.py
minibooks/ledger/tests.py
minibooks/ledger/urls.py
minibooks/ledger/views.py
minibooks/ledger/management/__init__.py
minibooks/ledger/management/commands/__init__.py
minibooks/ledger/management/commands/setup_demo.py
minibooks/ledger/templatetags/__init__.py
minibooks/ledger/templatetags/arrayutil.py
minibooks/ledger/templatetags/ledger.py
minibooks/media/css/django-contactinfo.css
minibooks/media/css/jquery.autocomplete.css
minibooks/media/css/jquery-ui/smoothness/jquery-ui-1.7.2.custom.css
minibooks/media/css/jquery-ui/smoothness/images/ui-bg_flat_0_aaaaaa_40x100.png
minibooks/media/css/jquery-ui/smoothness/images/ui-bg_flat_75_ffffff_40x100.png
minibooks/media/css/jquery-ui/smoothness/images/ui-bg_glass_55_fbf9ee_1x400.png
minibooks/media/css/jquery-ui/smoothness/images/ui-bg_glass_65_ffffff_1x400.png
minibooks/media/css/jquery-ui/smoothness/images/ui-bg_glass_75_dadada_1x400.png
minibooks/media/css/jquery-ui/smoothness/images/ui-bg_glass_75_e6e6e6_1x400.png
minibooks/media/css/jquery-ui/smoothness/images/ui-bg_glass_95_fef1ec_1x400.png
minibooks/media/css/jquery-ui/smoothness/images/ui-bg_highlight-soft_75_cccccc_1x100.png
minibooks/media/css/jquery-ui/smoothness/images/ui-icons_222222_256x240.png
minibooks/media/css/jquery-ui/smoothness/images/ui-icons_2e83ff_256x240.png
minibooks/media/css/jquery-ui/smoothness/images/ui-icons_454545_256x240.png
minibooks/media/css/jquery-ui/smoothness/images/ui-icons_888888_256x240.png
