Metadata-Version: 1.0
Name: minibooks
Version: 0.2.0
Summary: minibooks is a simple CRM, bookkeeping and double entry accounting package for the Django web framework.
Home-page: http://bitbucket.org/caktus/minibooks
Author: Caktus Consulting Group
Author-email: solutions@caktusgroup.com
License: LICENSE.txt
Platform: UNKNOWN
Classifier: Topic :: Internet :: WWW/HTTP :: Dynamic Content
Classifier: Intended Audience :: Developers
Classifier: License :: OSI Approved :: BSD License
Classifier: Programming Language :: Python
Classifier: Topic :: Software Development :: Libraries :: Python Modules
Classifier: Development Status :: 4 - Beta
Classifier: Operating System :: OS Independent
